base64Compressor/__init__.py
base64Compressor/__main__.py
base64Compressor/compressor.py
base64Compressor-0.2.0.dist-info/METADATA
base64Compressor-0.2.0.dist-info/WHEEL
base64Compressor-0.2.0.dist-info/entry_points.txt
base64Compressor-0.2.0.dist-info/top_level.txt
base64Compressor-0.2.0.dist-info/RECORD
